rogers/__init__.py
rogers/__main__.py
rogers/cli.py
rogers/config.py
rogers/default.ini
rogers/logger.py
rogers/store.py
rogers/util.py
rogers/visualize.py
rogers/data/__init__.py
rogers/data/features_pb2.py
rogers/data/yara/.git
rogers/data/yara/.gitmodules
rogers/data/yara/.travis.yml
rogers/data/yara/Antidebug_AntiVM_index.yar
rogers/data/yara/CVE_Rules_index.yar
rogers/data/yara/Crypto_index.yar
rogers/data/yara/Exploit-Kits_index.yar
rogers/data/yara/LICENSE
rogers/data/yara/Malicious_Documents_index.yar
rogers/data/yara/Mobile_Malware_index.yar
rogers/data/yara/Packers_index.yar
rogers/data/yara/README.md
rogers/data/yara/Webshells_index.yar
rogers/data/yara/email_index.yar
rogers/data/yara/index.yar
rogers/data/yara/index_gen.sh
rogers/data/yara/index_w_mobile.yar
rogers/data/yara/malware_index.yar
rogers/data/yara/Antidebug_AntiVM/antidebug_antivm.yar
rogers/data/yara/CVE_Rules/CVE-2010-0805.yar
rogers/data/yara/CVE_Rules/CVE-2010-0887.yar
rogers/data/yara/CVE_Rules/CVE-2010-1297.yar
rogers/data/yara/CVE_Rules/CVE-2012-0158.yar
rogers/data/yara/CVE_Rules/CVE-2013-0074.yar
rogers/data/yara/CVE_Rules/CVE-2013-0422.yar
rogers/data/yara/CVE_Rules/CVE-2015-1701.yar
rogers/data/yara/CVE_Rules/CVE-2015-2426.yar
rogers/data/yara/CVE_Rules/CVE-2015-2545.yar
rogers/data/yara/CVE_Rules/CVE-2015-5119.yar
rogers/data/yara/CVE_Rules/CVE-2016-5195.yar
rogers/data/yara/Crypto/crypto_signatures.yar
rogers/data/yara/Exploit-Kits/EK_Angler.yar
rogers/data/yara/Exploit-Kits/EK_Blackhole.yar
rogers/data/yara/Exploit-Kits/EK_BleedingLife.yar
rogers/data/yara/Exploit-Kits/EK_Crimepack.yar
rogers/data/yara/Exploit-Kits/EK_Eleonore.yar
rogers/data/yara/Exploit-Kits/EK_Fragus.yar
rogers/data/yara/Exploit-Kits/EK_Phoenix.yar
rogers/data/yara/Exploit-Kits/EK_Sakura.yar
rogers/data/yara/Exploit-Kits/EK_ZeroAcces.yar
rogers/data/yara/Exploit-Kits/EK_Zerox88.yar
rogers/data/yara/Exploit-Kits/EK_Zeus.yar
rogers-0.0.1.dist-info/DESCRIPTION.rst
rogers-0.0.1.dist-info/METADATA
rogers-0.0.1.dist-info/RECORD
rogers-0.0.1.dist-info/WHEEL
rogers-0.0.1.dist-info/entry_points.txt
rogers-0.0.1.dist-info/metadata.json
rogers-0.0.1.dist-info/top_level.txt
