Metadata-Version: 2.0
Name: rogers
Version: 0.0.1
Summary: Malware Similarity and Nearest Neighbor Tool
Home-page: UNKNOWN
Author: Matthew Maisel
Author-email: mmaisel@cylance.com
License: UNKNOWN
Platform: UNKNOWN
Requires-Dist: pefile (==2017.11.5)
Requires-Dist: uvloop (<1.0.0,>=0.9.1)
Requires-Dist: aiohttp (<2.4.0,>=2.3.5)
Requires-Dist: aioodbc (<0.3.0,>=0.2.0)
Requires-Dist: pandas (<0.22.0,>=0.21.1)
Requires-Dist: numpy (<1.14.0,>=1.13.3)
Requires-Dist: scipy (<1.1.0,>=1.0.0)
Requires-Dist: scikit-learn (<0.20.0,>=0.19.1)
Requires-Dist: ssdeep (<3.3,>=3.2)
Requires-Dist: yara-python (<3.8.0,>=3.7.0)
Requires-Dist: protobuf (<3.6.0,>=3.5.1)
Requires-Dist: nmslib (<1.7.0,>=1.6.0)
Requires-Dist: plotly (<2.3.0,>=2.2.3)
Requires-Dist: networkx (<2.1.0,>=2.0.0)
Requires-Dist: matplotlib (<2.2.0,>=2.1.1)
Requires-Dist: pygraphviz (<1.4.0,>=1.3.1)
Requires-Dist: terminaltables (<3.2.0,>=3.1.0)
Requires-Dist: pysparnn
